boot_dummy/__init__.py
boot_dummy/__main__.py
boot_dummy/dummy.py
boot_dummy-0.3.2.dist-info/METADATA
boot_dummy-0.3.2.dist-info/WHEEL
boot_dummy-0.3.2.dist-info/top_level.txt
boot_dummy-0.3.2.dist-info/RECORD
