Metadata-Version: 2.4
Name: boot_dummy
Version: 0.3.2
Summary: A Python package to create synthetic data with realistic statistical properties.
Author: Zak Remsik
Keywords: synthetic data,data generation,statistics
Requires-Python: >=3.8
Requires-Dist: pandas>=1.3.0
Requires-Dist: numpy>=1.20.0
